chibi_requests/__init__.py
chibi_requests/auth.py
chibi_requests/chibi_url.py
chibi_requests/other.py
chibi_requests/response.py
chibi_requests/status_code.py
chibi_requests-1.4.0.dist-info/licenses/AUTHORS.rst
chibi_requests-1.4.0.dist-info/licenses/LICENSE
chibi_requests-1.4.0.dist-info/METADATA
chibi_requests-1.4.0.dist-info/WHEEL
chibi_requests-1.4.0.dist-info/top_level.txt
chibi_requests-1.4.0.dist-info/RECORD
