Metadata-Version: 2.4
Name: chibi_requests
Version: 1.4.0
Summary: handle urls in a more easy and human way
Home-page: https://github.com/dem4ply/chibi_requests
Author: Dem4ply
Author-email: dem4ply@gmail.com
Keywords: chibi_requests
Classifier: Development Status :: 5 - Production/Stable
Classifier: Intended Audience :: Developers
Classifier: License :: Public Domain
Classifier: Natural Language :: English
Classifier: Natural Language :: Spanish
Classifier: Programming Language :: Python :: 3.7
Classifier: Programming Language :: Python :: 3.8
Classifier: Programming Language :: Python :: 3.9
Classifier: Programming Language :: Python :: 3.10
Classifier: Programming Language :: Python :: 3.11
Classifier: Programming Language :: Python :: 3.12
Classifier: Programming Language :: Python :: 3.13
Classifier: Programming Language :: Python :: 3.14
Classifier: Topic :: Utilities
Requires-Python: >=3.6
License-File: LICENSE
License-File: AUTHORS.rst
Requires-Dist: chibi>=0.10.0
Requires-Dist: requests>=2.22.0
Requires-Dist: beautifulsoup4>=4.8.0
Requires-Dist: marshmallow>=3.26.0
Dynamic: author
Dynamic: author-email
Dynamic: classifier
Dynamic: description
Dynamic: home-page
Dynamic: keywords
Dynamic: license-file
Dynamic: requires-dist
Dynamic: requires-python
Dynamic: summary
